django_schema_sprout/__init__.py
django_schema_sprout/apps.py
django_schema_sprout/models.py
django_schema_sprout/router.py
django_schema_sprout/schema_sprout.py
django_schema_sprout/db_inspectors/__init__.py
django_schema_sprout/db_inspectors/postgres_inspector.py
django_schema_sprout/utils/db_inspector.py
django_schema_sprout/utils/dynamic_model.py
django_schema_sprout/utils/dynamic_serializer.py
django_schema_sprout/utils/dynamic_view.py
django_schema_sprout/utils/singleton_class.py
django_schema_sprout-0.1.1.dist-info/METADATA
django_schema_sprout-0.1.1.dist-info/WHEEL
django_schema_sprout-0.1.1.dist-info/licenses/LICENSE
django_schema_sprout-0.1.1.dist-info/RECORD
