Metadata-Version: 2.1
Name: django-schema-sprout
Version: 0.1.1
Summary: Schema Sprout connects to a third-party database to dynamically create models and views.
Project-URL: Homepage, https://github.com/grumpy-miner/django-schema-sprout
Project-URL: Issues, https://github.com/grumpy-miner/django-schema-sprout/issues
Author-email: Paweł Puchalski <grumpy.miner.dev@gmail.com>
License-File: LICENSE
Classifier: License :: OSI Approved :: Apache Software License
Classifier: Operating System :: OS Independent
Classifier: Programming Language :: Python :: 3
Requires-Python: >=3.10
Requires-Dist: django<5.0,>=4.0
Requires-Dist: djangorestframework<4.0,>=3.14
Requires-Dist: drf-yasg<2.0,>=1.21.0
Provides-Extra: dev
Requires-Dist: black~=23.12.1; extra == 'dev'
Requires-Dist: build~=1.0.3; extra == 'dev'
Requires-Dist: flake8~=7.0.0; extra == 'dev'
Provides-Extra: test
Requires-Dist: pytest-cov~=4.1.0; extra == 'test'
Requires-Dist: pytest-django~=4.7.0; extra == 'test'
Requires-Dist: pytest-postgresql~=5.0.0; extra == 'test'
Requires-Dist: pytest~=7.3.1; extra == 'test'
